fsapp/__init__.py
fsapp/__main__.py
fsapp/base.py
fsapp/classes.py
fsapp/logger.py
fsapp/test_server.py
fsapp/api/__init__.py
fsapp/api/routers.py
fsapp/api/endpoints/__init__.py
fsapp/api/endpoints/auth.py
fsapp/api/endpoints/search.py
fsapp/api/endpoints/utils.py
fsapp/api/schemas/__init__.py
fsapp/api/schemas/requests.py
fsapp/api/schemas/responses.py
fsapp/core/__init__.py
fsapp/core/config.py
fsapp/core/handlers.py
fsapp-2.0.0.dist-info/LICENSE
fsapp-2.0.0.dist-info/METADATA
fsapp-2.0.0.dist-info/WHEEL
fsapp-2.0.0.dist-info/top_level.txt
fsapp-2.0.0.dist-info/RECORD
