Metadata-Version: 2.1
Name: fsapp
Version: 2.0.0
Summary: Fastapi web-app
Author-email: Scrandi Coulson <scrandi.coulson@ro.ru>
Classifier: Programming Language :: Python :: 3
Classifier: License :: OSI Approved :: MIT License
Classifier: Operating System :: OS Independent
Requires-Python: >=3.9
License-File: LICENSE
Requires-Dist: anyio ==3.6.2
Requires-Dist: attrs ==22.2.0
Requires-Dist: click ==8.1.3
Requires-Dist: colorama
Requires-Dist: dynaconf ==3.1.12
Requires-Dist: exceptiongroup ==1.1.1
Requires-Dist: fastapi ==0.94.0
Requires-Dist: h11 ==0.14.0
Requires-Dist: idna ==3.4
Requires-Dist: iniconfig ==2.0.0
Requires-Dist: packaging ==23.0
Requires-Dist: pluggy ==1.0.0
Requires-Dist: pydantic ==1.10.6
Requires-Dist: pytest ==7.2.2
Requires-Dist: sniffio ==1.3.0
Requires-Dist: starlette ==0.26.0.post1
Requires-Dist: tomli ==2.0.1
Requires-Dist: typing-extensions ==4.5.0
Requires-Dist: uvicorn ==0.21.0
Requires-Dist: python-multipart ==0.0.6
Requires-Dist: toml ==0.10.2
Requires-Dist: prettytable ==3.7.0
Requires-Dist: structlog ==24.1.0
Requires-Dist: orjson ==3.9.12
